{
  "competitionType": "cotd",
  "competitionLabel": "Cup of the Day",
  "eventLabel": "COTD 79",
  "nr": 79,
  "map": "CotD - Athene's Revenge",
  "author": "Ryuji & Ultimate Billy",
  "description": null,
  "fastestTime": "42.884",
  "fastestTimeDriver": "[CTR]Kernkob",
  "fastestTimeRound": "Final",
  "rouletteSourceLabel": null,
  "sourceFile": "COTDs 76-100 - COTD 76-80.csv",
  "results": [
    {
      "placing": 1,
      "name": "[CTR]Kernkob",
      "time": "42.884",
      "eliminationRound": null,
      "rouletteMap": null,
      "rouletteMapper": null,
      "rouletteSourceEventNumber": null
    },
    {
      "placing": 2,
      "name": "[CTR]Hydro",
      "time": "43.083",
      "eliminationRound": "18",
      "rouletteMap": null,
      "rouletteMapper": null,
      "rouletteSourceEventNumber": null
    },
    {
      "placing": 3,
      "name": "ZOMAN",
      "time": "43.214",
      "eliminationRound": "17",
      "rouletteMap": null,
      "rouletteMapper": null,
      "rouletteSourceEventNumber": null
    },
    {
      "placing": 4,
      "name": "[KURK] Quickracer10",
      "time": "43.226",
      "eliminationRound": "16",
      "rouletteMap": null,
      "rouletteMapper": null,
      "rouletteSourceEventNumber": null
    },
    {
      "placing": 5,
      "name": "justMaki",
      "time": "43.319",
      "eliminationRound": "15",
      "rouletteMap": null,
      "rouletteMapper": null,
      "rouletteSourceEventNumber": null
    },
    {
      "placing": 6,
      "name": "[CTR]Cbad Cruiser",
      "time": "43.469",
      "eliminationRound": "14",
      "rouletteMap": null,
      "rouletteMapper": null,
      "rouletteSourceEventNumber": null
    },
    {
      "placing": 7,
      "name": "Lexer",
      "time": "43.577",
      "eliminationRound": "13",
      "rouletteMap": null,
      "rouletteMapper": null,
      "rouletteSourceEventNumber": null
    },
    {
      "placing": 8,
      "name": "St Nicholas",
      "time": "43.993",
      "eliminationRound": "13",
      "rouletteMap": null,
      "rouletteMapper": null,
      "rouletteSourceEventNumber": null
    },
    {
      "placing": 9,
      "name": "[CTR] Sandals",
      "time": "43.692",
      "eliminationRound": "12",
      "rouletteMap": null,
      "rouletteMapper": null,
      "rouletteSourceEventNumber": null
    },
    {
      "placing": 10,
      "name": "Northwind",
      "time": "43.775",
      "eliminationRound": "12",
      "rouletteMap": null,
      "rouletteMapper": null,
      "rouletteSourceEventNumber": null
    },
    {
      "placing": 11,
      "name": "[ZET]MackCheesy",
      "time": "43.934",
      "eliminationRound": "11",
      "rouletteMap": null,
      "rouletteMapper": null,
      "rouletteSourceEventNumber": null
    },
    {
      "placing": 12,
      "name": "Murrl",
      "time": "44.407",
      "eliminationRound": "11",
      "rouletteMap": null,
      "rouletteMapper": null,
      "rouletteSourceEventNumber": null
    },
    {
      "placing": 13,
      "name": "agix",
      "time": "44.184",
      "eliminationRound": "10",
      "rouletteMap": null,
      "rouletteMapper": null,
      "rouletteSourceEventNumber": null
    },
    {
      "placing": 14,
      "name": "[CTR] PoopSheriff",
      "time": "44.224",
      "eliminationRound": "10",
      "rouletteMap": null,
      "rouletteMapper": null,
      "rouletteSourceEventNumber": null
    },
    {
      "placing": 15,
      "name": "Grimmlon",
      "time": "44.281",
      "eliminationRound": "10",
      "rouletteMap": null,
      "rouletteMapper": null,
      "rouletteSourceEventNumber": null
    },
    {
      "placing": 16,
      "name": "Joking",
      "time": "44.380",
      "eliminationRound": "10",
      "rouletteMap": null,
      "rouletteMapper": null,
      "rouletteSourceEventNumber": null
    },
    {
      "placing": 17,
      "name": "M4rv1nDD",
      "time": "44.533",
      "eliminationRound": "9",
      "rouletteMap": null,
      "rouletteMapper": null,
      "rouletteSourceEventNumber": null
    },
    {
      "placing": 18,
      "name": "Kaiser64",
      "time": "44.611",
      "eliminationRound": "9",
      "rouletteMap": null,
      "rouletteMapper": null,
      "rouletteSourceEventNumber": null
    },
    {
      "placing": 19,
      "name": "[CTR]Mμ",
      "time": "DNF",
      "eliminationRound": "9",
      "rouletteMap": null,
      "rouletteMapper": null,
      "rouletteSourceEventNumber": null
    },
    {
      "placing": 19,
      "name": "Shadynook",
      "time": "DNF",
      "eliminationRound": "9",
      "rouletteMap": null,
      "rouletteMapper": null,
      "rouletteSourceEventNumber": null
    },
    {
      "placing": 21,
      "name": "Tommygaming5132",
      "time": "44.440",
      "eliminationRound": "8",
      "rouletteMap": null,
      "rouletteMapper": null,
      "rouletteSourceEventNumber": null
    },
    {
      "placing": 22,
      "name": "[ZET] Wheelie",
      "time": "44.464",
      "eliminationRound": "8",
      "rouletteMap": null,
      "rouletteMapper": null,
      "rouletteSourceEventNumber": null
    },
    {
      "placing": 23,
      "name": "[CTR]GuAlexItar",
      "time": "44.684",
      "eliminationRound": "8",
      "rouletteMap": null,
      "rouletteMapper": null,
      "rouletteSourceEventNumber": null
    },
    {
      "placing": 24,
      "name": "palfly",
      "time": "44.962",
      "eliminationRound": "8",
      "rouletteMap": null,
      "rouletteMapper": null,
      "rouletteSourceEventNumber": null
    },
    {
      "placing": 25,
      "name": "[CTR]OwlPlague",
      "time": "45.069",
      "eliminationRound": "7",
      "rouletteMap": null,
      "rouletteMapper": null,
      "rouletteSourceEventNumber": null
    },
    {
      "placing": 26,
      "name": "DeiRex",
      "time": "45.267",
      "eliminationRound": "7",
      "rouletteMap": null,
      "rouletteMapper": null,
      "rouletteSourceEventNumber": null
    },
    {
      "placing": 27,
      "name": "[TOG]Lazy_Echidna",
      "time": "45.300",
      "eliminationRound": "7",
      "rouletteMap": null,
      "rouletteMapper": null,
      "rouletteSourceEventNumber": null
    },
    {
      "placing": 28,
      "name": "[GLHF]loganbradley714",
      "time": "45.589",
      "eliminationRound": "7",
      "rouletteMap": null,
      "rouletteMapper": null,
      "rouletteSourceEventNumber": null
    },
    {
      "placing": 29,
      "name": "Weak_Knees",
      "time": "45.169",
      "eliminationRound": "6",
      "rouletteMap": null,
      "rouletteMapper": null,
      "rouletteSourceEventNumber": null
    },
    {
      "placing": 30,
      "name": "ferinine",
      "time": "45.609",
      "eliminationRound": "6",
      "rouletteMap": null,
      "rouletteMapper": null,
      "rouletteSourceEventNumber": null
    },
    {
      "placing": 31,
      "name": "Bank Waffles",
      "time": "DNF",
      "eliminationRound": "6",
      "rouletteMap": null,
      "rouletteMapper": null,
      "rouletteSourceEventNumber": null
    },
    {
      "placing": 31,
      "name": "Kiprosa",
      "time": "DNF",
      "eliminationRound": "6",
      "rouletteMap": null,
      "rouletteMapper": null,
      "rouletteSourceEventNumber": null
    },
    {
      "placing": 33,
      "name": "[ZET]frenchteost",
      "time": "45.689",
      "eliminationRound": "5",
      "rouletteMap": null,
      "rouletteMapper": null,
      "rouletteSourceEventNumber": null
    },
    {
      "placing": 34,
      "name": "Mortishade",
      "time": "46.146",
      "eliminationRound": "5",
      "rouletteMap": null,
      "rouletteMapper": null,
      "rouletteSourceEventNumber": null
    },
    {
      "placing": 35,
      "name": "Ender",
      "time": "46.408",
      "eliminationRound": "5",
      "rouletteMap": null,
      "rouletteMapper": null,
      "rouletteSourceEventNumber": null
    },
    {
      "placing": 36,
      "name": "OLR94",
      "time": "50.925",
      "eliminationRound": "5",
      "rouletteMap": null,
      "rouletteMapper": null,
      "rouletteSourceEventNumber": null
    },
    {
      "placing": 37,
      "name": "[ZET]LILWOOLEY",
      "time": "49.264",
      "eliminationRound": "4",
      "rouletteMap": null,
      "rouletteMapper": null,
      "rouletteSourceEventNumber": null
    },
    {
      "placing": 38,
      "name": "snugglykitty",
      "time": "51.013",
      "eliminationRound": "4",
      "rouletteMap": null,
      "rouletteMapper": null,
      "rouletteSourceEventNumber": null
    },
    {
      "placing": 39,
      "name": "[gorp]//////void",
      "time": "DNF",
      "eliminationRound": "4",
      "rouletteMap": null,
      "rouletteMapper": null,
      "rouletteSourceEventNumber": null
    },
    {
      "placing": 40,
      "name": "cookie",
      "time": "DNF",
      "eliminationRound": "4",
      "rouletteMap": null,
      "rouletteMapper": null,
      "rouletteSourceEventNumber": null
    },
    {
      "placing": 41,
      "name": "variableferret",
      "time": "50.121",
      "eliminationRound": "3",
      "rouletteMap": null,
      "rouletteMapper": null,
      "rouletteSourceEventNumber": null
    },
    {
      "placing": 42,
      "name": "Form",
      "time": "50.831",
      "eliminationRound": "3",
      "rouletteMap": null,
      "rouletteMapper": null,
      "rouletteSourceEventNumber": null
    },
    {
      "placing": 43,
      "name": "icRS",
      "time": "DNF",
      "eliminationRound": "3",
      "rouletteMap": null,
      "rouletteMapper": null,
      "rouletteSourceEventNumber": null
    },
    {
      "placing": 43,
      "name": "gatlinggun511",
      "time": "DNF",
      "eliminationRound": "3",
      "rouletteMap": null,
      "rouletteMapper": null,
      "rouletteSourceEventNumber": null
    },
    {
      "placing": 45,
      "name": "redal",
      "time": "50.283",
      "eliminationRound": "2",
      "rouletteMap": null,
      "rouletteMapper": null,
      "rouletteSourceEventNumber": null
    },
    {
      "placing": 46,
      "name": "Noxitu",
      "time": "DNF",
      "eliminationRound": "2",
      "rouletteMap": null,
      "rouletteMapper": null,
      "rouletteSourceEventNumber": null
    },
    {
      "placing": 46,
      "name": "imagineaclevernamehere",
      "time": "DNF",
      "eliminationRound": "2",
      "rouletteMap": null,
      "rouletteMapper": null,
      "rouletteSourceEventNumber": null
    },
    {
      "placing": 46,
      "name": "[ZET]vectortrajector",
      "time": "DNF",
      "eliminationRound": "2",
      "rouletteMap": null,
      "rouletteMapper": null,
      "rouletteSourceEventNumber": null
    },
    {
      "placing": 51,
      "name": "SkyVirus",
      "time": "DNF",
      "eliminationRound": "1",
      "rouletteMap": null,
      "rouletteMapper": null,
      "rouletteSourceEventNumber": null
    },
    {
      "placing": 51,
      "name": "Sprinty",
      "time": "DNF",
      "eliminationRound": "1",
      "rouletteMap": null,
      "rouletteMapper": null,
      "rouletteSourceEventNumber": null
    },
    {
      "placing": 51,
      "name": "[ZET]Sword125",
      "time": "DNF",
      "eliminationRound": "1",
      "rouletteMap": null,
      "rouletteMapper": null,
      "rouletteSourceEventNumber": null
    }
  ]
}
