{
  "competitionType": "cotd",
  "competitionLabel": "Cup of the Day",
  "eventLabel": "COTD 17",
  "nr": 17,
  "map": "COTD - Murky Castle",
  "author": "Bottomless & Renergy",
  "description": null,
  "fastestTime": "41.875",
  "fastestTimeDriver": "[CTR] jandje",
  "fastestTimeRound": "Round 1",
  "rouletteSourceLabel": null,
  "sourceFile": "COTDs 1-25 - COTD 16-20.csv",
  "results": [
    {
      "placing": 1,
      "name": "Erko",
      "time": "42.435",
      "eliminationRound": null,
      "rouletteMap": null,
      "rouletteMapper": null,
      "rouletteSourceEventNumber": null
    },
    {
      "placing": 2,
      "name": "justMaki",
      "time": "42.647",
      "eliminationRound": "15",
      "rouletteMap": null,
      "rouletteMapper": null,
      "rouletteSourceEventNumber": null
    },
    {
      "placing": 3,
      "name": "[CTR] jandje",
      "time": "43.734",
      "eliminationRound": "14",
      "rouletteMap": null,
      "rouletteMapper": null,
      "rouletteSourceEventNumber": null
    },
    {
      "placing": 4,
      "name": "[OREO]Pigbuy",
      "time": "42.408",
      "eliminationRound": "13",
      "rouletteMap": null,
      "rouletteMapper": null,
      "rouletteSourceEventNumber": null
    },
    {
      "placing": 5,
      "name": "schmxrg",
      "time": "42.570",
      "eliminationRound": "12",
      "rouletteMap": null,
      "rouletteMapper": null,
      "rouletteSourceEventNumber": null
    },
    {
      "placing": 6,
      "name": "[CTR] Sandals",
      "time": "42.894",
      "eliminationRound": "11",
      "rouletteMap": null,
      "rouletteMapper": null,
      "rouletteSourceEventNumber": null
    },
    {
      "placing": 7,
      "name": "[CTR]Cbad Cruiser",
      "time": "42.786",
      "eliminationRound": "10",
      "rouletteMap": null,
      "rouletteMapper": null,
      "rouletteSourceEventNumber": null
    },
    {
      "placing": 8,
      "name": "[KURK] Quickracer10",
      "time": "43.182",
      "eliminationRound": "10",
      "rouletteMap": null,
      "rouletteMapper": null,
      "rouletteSourceEventNumber": null
    },
    {
      "placing": 9,
      "name": "Vigi",
      "time": "42.861",
      "eliminationRound": "9",
      "rouletteMap": null,
      "rouletteMapper": null,
      "rouletteSourceEventNumber": null
    },
    {
      "placing": 10,
      "name": "A Broken Forklift",
      "time": "43.178",
      "eliminationRound": "9",
      "rouletteMap": null,
      "rouletteMapper": null,
      "rouletteSourceEventNumber": null
    },
    {
      "placing": 11,
      "name": "Zodiak",
      "time": "43.534",
      "eliminationRound": "8",
      "rouletteMap": null,
      "rouletteMapper": null,
      "rouletteSourceEventNumber": null
    },
    {
      "placing": 12,
      "name": "AndMe14",
      "time": "DNF",
      "eliminationRound": "8",
      "rouletteMap": null,
      "rouletteMapper": null,
      "rouletteSourceEventNumber": null
    },
    {
      "placing": 14,
      "name": "A2 Zecklord",
      "time": "DNF",
      "eliminationRound": "7",
      "rouletteMap": null,
      "rouletteMapper": null,
      "rouletteSourceEventNumber": null
    },
    {
      "placing": 14,
      "name": "[CTR]TheBamboozler",
      "time": "DNF",
      "eliminationRound": "7",
      "rouletteMap": null,
      "rouletteMapper": null,
      "rouletteSourceEventNumber": null
    },
    {
      "placing": 15,
      "name": "St Nicholas",
      "time": "43.114",
      "eliminationRound": "6",
      "rouletteMap": null,
      "rouletteMapper": null,
      "rouletteSourceEventNumber": null
    },
    {
      "placing": 16,
      "name": "Lazy_Echidna",
      "time": "43.146",
      "eliminationRound": "6",
      "rouletteMap": null,
      "rouletteMapper": null,
      "rouletteSourceEventNumber": null
    },
    {
      "placing": 17,
      "name": "JobW",
      "time": "43.171",
      "eliminationRound": "6",
      "rouletteMap": null,
      "rouletteMapper": null,
      "rouletteSourceEventNumber": null
    },
    {
      "placing": 18,
      "name": "[CTR]TwoFace",
      "time": "43.497",
      "eliminationRound": "6",
      "rouletteMap": null,
      "rouletteMapper": null,
      "rouletteSourceEventNumber": null
    },
    {
      "placing": 19,
      "name": "[BGR] Joking",
      "time": "43.307",
      "eliminationRound": "5",
      "rouletteMap": null,
      "rouletteMapper": null,
      "rouletteSourceEventNumber": null
    },
    {
      "placing": 20,
      "name": "Zarro",
      "time": "43.334",
      "eliminationRound": "5",
      "rouletteMap": null,
      "rouletteMapper": null,
      "rouletteSourceEventNumber": null
    },
    {
      "placing": 21,
      "name": "Tritonas1237",
      "time": "43.470",
      "eliminationRound": "5",
      "rouletteMap": null,
      "rouletteMapper": null,
      "rouletteSourceEventNumber": null
    },
    {
      "placing": 22,
      "name": "Sterben",
      "time": "43.489",
      "eliminationRound": "5",
      "rouletteMap": null,
      "rouletteMapper": null,
      "rouletteSourceEventNumber": null
    },
    {
      "placing": 23,
      "name": "[CTR]R0nanC",
      "time": "43.624",
      "eliminationRound": "4",
      "rouletteMap": null,
      "rouletteMapper": null,
      "rouletteSourceEventNumber": null
    },
    {
      "placing": 24,
      "name": "Lexer",
      "time": "43.844",
      "eliminationRound": "4",
      "rouletteMap": null,
      "rouletteMapper": null,
      "rouletteSourceEventNumber": null
    },
    {
      "placing": 25,
      "name": "snorReplay",
      "time": "43.994",
      "eliminationRound": "4",
      "rouletteMap": null,
      "rouletteMapper": null,
      "rouletteSourceEventNumber": null
    },
    {
      "placing": 26,
      "name": "Beans",
      "time": "44.562",
      "eliminationRound": "4",
      "rouletteMap": null,
      "rouletteMapper": null,
      "rouletteSourceEventNumber": null
    },
    {
      "placing": 27,
      "name": "Hi Im Yolo",
      "time": "43.667",
      "eliminationRound": "3",
      "rouletteMap": null,
      "rouletteMapper": null,
      "rouletteSourceEventNumber": null
    },
    {
      "placing": 28,
      "name": "Shadynook",
      "time": "43.681",
      "eliminationRound": "3",
      "rouletteMap": null,
      "rouletteMapper": null,
      "rouletteSourceEventNumber": null
    },
    {
      "placing": 29,
      "name": "DeiRex",
      "time": "43.692",
      "eliminationRound": "3",
      "rouletteMap": null,
      "rouletteMapper": null,
      "rouletteSourceEventNumber": null
    },
    {
      "placing": 30,
      "name": "RoundNzt",
      "time": "44.353",
      "eliminationRound": "3",
      "rouletteMap": null,
      "rouletteMapper": null,
      "rouletteSourceEventNumber": null
    },
    {
      "placing": 31,
      "name": "JaBabbit",
      "time": "44.135",
      "eliminationRound": "2",
      "rouletteMap": null,
      "rouletteMapper": null,
      "rouletteSourceEventNumber": null
    },
    {
      "placing": 32,
      "name": "Arder",
      "time": "44.562",
      "eliminationRound": "2",
      "rouletteMap": null,
      "rouletteMapper": null,
      "rouletteSourceEventNumber": null
    },
    {
      "placing": 33,
      "name": "Sir Not Nub",
      "time": "44.691",
      "eliminationRound": "2",
      "rouletteMap": null,
      "rouletteMapper": null,
      "rouletteSourceEventNumber": null
    },
    {
      "placing": 34,
      "name": "Zaza_Lord",
      "time": "DNF",
      "eliminationRound": "2",
      "rouletteMap": null,
      "rouletteMapper": null,
      "rouletteSourceEventNumber": null
    },
    {
      "placing": 35,
      "name": "cookie",
      "time": "45.210",
      "eliminationRound": "1",
      "rouletteMap": null,
      "rouletteMapper": null,
      "rouletteSourceEventNumber": null
    },
    {
      "placing": 36,
      "name": "FArd_gamin",
      "time": "45.339",
      "eliminationRound": "1",
      "rouletteMap": null,
      "rouletteMapper": null,
      "rouletteSourceEventNumber": null
    },
    {
      "placing": 37,
      "name": "sharkoftheday",
      "time": "45.994",
      "eliminationRound": "1",
      "rouletteMap": null,
      "rouletteMapper": null,
      "rouletteSourceEventNumber": null
    }
  ]
}
