{
  "competitionType": "cotd",
  "competitionLabel": "Cup of the Day",
  "eventLabel": "COTW 59",
  "nr": 59,
  "map": "COTD-Limit Zero",
  "author": "[ATB] reholmes92",
  "description": null,
  "fastestTime": "38.784",
  "fastestTimeDriver": "RoundNzt",
  "fastestTimeRound": "Round 10",
  "rouletteSourceLabel": null,
  "sourceFile": "COTDs 51-75 - COTD 56-60.csv",
  "results": [
    {
      "placing": 1,
      "name": "[CTR] Hydro",
      "time": "38.866",
      "eliminationRound": null,
      "rouletteMap": null,
      "rouletteMapper": null,
      "rouletteSourceEventNumber": null
    },
    {
      "placing": 2,
      "name": "[CTR] jandje",
      "time": "38.883",
      "eliminationRound": "14",
      "rouletteMap": null,
      "rouletteMapper": null,
      "rouletteSourceEventNumber": null
    },
    {
      "placing": 3,
      "name": "[oops] Wombat!",
      "time": "39.001",
      "eliminationRound": "13",
      "rouletteMap": null,
      "rouletteMapper": null,
      "rouletteSourceEventNumber": null
    },
    {
      "placing": 4,
      "name": "Lexer",
      "time": "38.985",
      "eliminationRound": "12",
      "rouletteMap": null,
      "rouletteMapper": null,
      "rouletteSourceEventNumber": null
    },
    {
      "placing": 5,
      "name": "RoundNzt",
      "time": "39.019",
      "eliminationRound": "11",
      "rouletteMap": null,
      "rouletteMapper": null,
      "rouletteSourceEventNumber": null
    },
    {
      "placing": 6,
      "name": "R0nanC",
      "time": "39.148",
      "eliminationRound": "10",
      "rouletteMap": null,
      "rouletteMapper": null,
      "rouletteSourceEventNumber": null
    },
    {
      "placing": 7,
      "name": "PoopSheriff",
      "time": "39.030",
      "eliminationRound": "9",
      "rouletteMap": null,
      "rouletteMapper": null,
      "rouletteSourceEventNumber": null
    },
    {
      "placing": 8,
      "name": "Shadynook",
      "time": "39.317",
      "eliminationRound": "9",
      "rouletteMap": null,
      "rouletteMapper": null,
      "rouletteSourceEventNumber": null
    },
    {
      "placing": 9,
      "name": "Butter",
      "time": "39.116",
      "eliminationRound": "8",
      "rouletteMap": null,
      "rouletteMapper": null,
      "rouletteSourceEventNumber": null
    },
    {
      "placing": 10,
      "name": "Northwind",
      "time": "39.189",
      "eliminationRound": "8",
      "rouletteMap": null,
      "rouletteMapper": null,
      "rouletteSourceEventNumber": null
    },
    {
      "placing": 11,
      "name": "Es3en",
      "time": "39.220",
      "eliminationRound": "7",
      "rouletteMap": null,
      "rouletteMapper": null,
      "rouletteSourceEventNumber": null
    },
    {
      "placing": 12,
      "name": "Pants",
      "time": "39.380",
      "eliminationRound": "7",
      "rouletteMap": null,
      "rouletteMapper": null,
      "rouletteSourceEventNumber": null
    },
    {
      "placing": 13,
      "name": "EMel_",
      "time": "39.224",
      "eliminationRound": "6",
      "rouletteMap": null,
      "rouletteMapper": null,
      "rouletteSourceEventNumber": null
    },
    {
      "placing": 14,
      "name": "PandaMane",
      "time": "39.267",
      "eliminationRound": "6",
      "rouletteMap": null,
      "rouletteMapper": null,
      "rouletteSourceEventNumber": null
    },
    {
      "placing": 15,
      "name": "[TOG] Lazy_Echidna",
      "time": "39.286",
      "eliminationRound": "6",
      "rouletteMap": null,
      "rouletteMapper": null,
      "rouletteSourceEventNumber": null
    },
    {
      "placing": 16,
      "name": "St Nicholas",
      "time": "39.292",
      "eliminationRound": "6",
      "rouletteMap": null,
      "rouletteMapper": null,
      "rouletteSourceEventNumber": null
    },
    {
      "placing": 17,
      "name": "agix",
      "time": "39.340",
      "eliminationRound": "5",
      "rouletteMap": null,
      "rouletteMapper": null,
      "rouletteSourceEventNumber": null
    },
    {
      "placing": 18,
      "name": "DeiRex",
      "time": "39.429",
      "eliminationRound": "5",
      "rouletteMap": null,
      "rouletteMapper": null,
      "rouletteSourceEventNumber": null
    },
    {
      "placing": 19,
      "name": "sobeisgood",
      "time": "39.469",
      "eliminationRound": "5",
      "rouletteMap": null,
      "rouletteMapper": null,
      "rouletteSourceEventNumber": null
    },
    {
      "placing": 20,
      "name": "[ZMS] Metalted",
      "time": "39.474",
      "eliminationRound": "5",
      "rouletteMap": null,
      "rouletteMapper": null,
      "rouletteSourceEventNumber": null
    },
    {
      "placing": 21,
      "name": "Hi Im Yolo",
      "time": "39.581",
      "eliminationRound": "4",
      "rouletteMap": null,
      "rouletteMapper": null,
      "rouletteSourceEventNumber": null
    },
    {
      "placing": 22,
      "name": "Nails",
      "time": "39.584",
      "eliminationRound": "4",
      "rouletteMap": null,
      "rouletteMapper": null,
      "rouletteSourceEventNumber": null
    },
    {
      "placing": 23,
      "name": "Weak_Knees",
      "time": "39.615",
      "eliminationRound": "4",
      "rouletteMap": null,
      "rouletteMapper": null,
      "rouletteSourceEventNumber": null
    },
    {
      "placing": 24,
      "name": "Matic_D",
      "time": "DNF",
      "eliminationRound": "4",
      "rouletteMap": null,
      "rouletteMapper": null,
      "rouletteSourceEventNumber": null
    },
    {
      "placing": 25,
      "name": "maxie12",
      "time": "39.948",
      "eliminationRound": "3",
      "rouletteMap": null,
      "rouletteMapper": null,
      "rouletteSourceEventNumber": null
    },
    {
      "placing": 26,
      "name": "[ZET] LILWOOLEY",
      "time": "39.965",
      "eliminationRound": "3",
      "rouletteMap": null,
      "rouletteMapper": null,
      "rouletteSourceEventNumber": null
    },
    {
      "placing": 27,
      "name": "cookie",
      "time": "40.209",
      "eliminationRound": "3",
      "rouletteMap": null,
      "rouletteMapper": null,
      "rouletteSourceEventNumber": null
    },
    {
      "placing": 28,
      "name": "[ZET] Wheelie",
      "time": "40.766",
      "eliminationRound": "3",
      "rouletteMap": null,
      "rouletteMapper": null,
      "rouletteSourceEventNumber": null
    },
    {
      "placing": 29,
      "name": "Alaskaman79",
      "time": "40.068",
      "eliminationRound": "2",
      "rouletteMap": null,
      "rouletteMapper": null,
      "rouletteSourceEventNumber": null
    },
    {
      "placing": 30,
      "name": "azebramoomoo",
      "time": "40.438",
      "eliminationRound": "2",
      "rouletteMap": null,
      "rouletteMapper": null,
      "rouletteSourceEventNumber": null
    },
    {
      "placing": 31,
      "name": "[RB] Chinpokomon",
      "time": "DNF",
      "eliminationRound": "2",
      "rouletteMap": null,
      "rouletteMapper": null,
      "rouletteSourceEventNumber": null
    },
    {
      "placing": 31,
      "name": "Mr. Cranky",
      "time": "DNF",
      "eliminationRound": "2",
      "rouletteMap": null,
      "rouletteMapper": null,
      "rouletteSourceEventNumber": null
    },
    {
      "placing": 33,
      "name": "Gzusmon",
      "time": "41.353",
      "eliminationRound": "1",
      "rouletteMap": null,
      "rouletteMapper": null,
      "rouletteSourceEventNumber": null
    },
    {
      "placing": 34,
      "name": "Razboy20",
      "time": "41.451",
      "eliminationRound": "1",
      "rouletteMap": null,
      "rouletteMapper": null,
      "rouletteSourceEventNumber": null
    },
    {
      "placing": 35,
      "name": "[ZET] vectortrajector",
      "time": "DNF",
      "eliminationRound": "1",
      "rouletteMap": null,
      "rouletteMapper": null,
      "rouletteSourceEventNumber": null
    },
    {
      "placing": 35,
      "name": "it_is_nic",
      "time": "DNF",
      "eliminationRound": "1",
      "rouletteMap": null,
      "rouletteMapper": null,
      "rouletteSourceEventNumber": null
    }
  ]
}
